framesh/__init__.py
framesh/board.py
framesh/flare.py
framesh/gframes.py
framesh/py.typed
framesh/rops.py
framesh/shot.py
framesh/toldi.py
framesh/util.py
framesh-0.3.dist-info/LICENSE
framesh-0.3.dist-info/METADATA
framesh-0.3.dist-info/WHEEL
framesh-0.3.dist-info/top_level.txt
framesh-0.3.dist-info/RECORD
