Metadata-Version: 2.1
Name: framesh
Version: 0.3
Summary: Local reference frame algorithms for meshes
Author-email: Luca Grementieri <luca.grementieri@ens-paris-saclay.fr>
Project-URL: Repository, https://github.com/lucagrementieri/framesh
Project-URL: Issues, https://github.com/lucagrementieri/framesh/issues
Keywords: 3d,mesh,geometry,local-reference-frame,computer-graphics,computational-geometry,point-cloud
Classifier: Development Status :: 3 - Alpha
Classifier: Intended Audience :: Science/Research
Classifier: License :: OSI Approved :: MIT License
Classifier: Natural Language :: English
Classifier: Operating System :: OS Independent
Classifier: Programming Language :: Python :: 3
Classifier: Programming Language :: Python :: 3.10
Classifier: Programming Language :: Python :: 3.11
Classifier: Programming Language :: Python :: 3.12
Classifier: Topic :: Multimedia :: Graphics :: 3D Modeling
Classifier: Topic :: Scientific/Engineering :: Mathematics
Requires-Python: >=3.10
License-File: LICENSE
Requires-Dist: networkx
Requires-Dist: numpy
Requires-Dist: scipy
Requires-Dist: shapely>=2
Requires-Dist: trimesh>=4
Provides-Extra: test
Requires-Dist: mypy~=1.13; extra == "test"
Requires-Dist: pip-tools~=7.4; extra == "test"
Requires-Dist: pytest~=8.3; extra == "test"
Requires-Dist: ruff~=0.8; extra == "test"
Requires-Dist: scipy-stubs~=1.14; extra == "test"
